odoo/addons/project_recalculate/README.rst
odoo/addons/project_recalculate/__init__.py
odoo/addons/project_recalculate/__manifest__.py
odoo/addons/project_recalculate/i18n/am.po
odoo/addons/project_recalculate/i18n/ar.po
odoo/addons/project_recalculate/i18n/bg.po
odoo/addons/project_recalculate/i18n/bs.po
odoo/addons/project_recalculate/i18n/ca.po
odoo/addons/project_recalculate/i18n/ca_ES.po
odoo/addons/project_recalculate/i18n/cs.po
odoo/addons/project_recalculate/i18n/da.po
odoo/addons/project_recalculate/i18n/de.po
odoo/addons/project_recalculate/i18n/el.po
odoo/addons/project_recalculate/i18n/el_GR.po
odoo/addons/project_recalculate/i18n/en_AU.po
odoo/addons/project_recalculate/i18n/en_GB.po
odoo/addons/project_recalculate/i18n/es.po
odoo/addons/project_recalculate/i18n/es_AR.po
odoo/addons/project_recalculate/i18n/es_CL.po
odoo/addons/project_recalculate/i18n/es_CO.po
odoo/addons/project_recalculate/i18n/es_CR.po
odoo/addons/project_recalculate/i18n/es_DO.po
odoo/addons/project_recalculate/i18n/es_EC.po
odoo/addons/project_recalculate/i18n/es_ES.po
odoo/addons/project_recalculate/i18n/es_MX.po
odoo/addons/project_recalculate/i18n/es_PE.po
odoo/addons/project_recalculate/i18n/es_PY.po
odoo/addons/project_recalculate/i18n/es_VE.po
odoo/addons/project_recalculate/i18n/et.po
odoo/addons/project_recalculate/i18n/eu.po
odoo/addons/project_recalculate/i18n/fa.po
odoo/addons/project_recalculate/i18n/fi.po
odoo/addons/project_recalculate/i18n/fr.po
odoo/addons/project_recalculate/i18n/fr_CA.po
odoo/addons/project_recalculate/i18n/fr_CH.po
odoo/addons/project_recalculate/i18n/fr_FR.po
odoo/addons/project_recalculate/i18n/gl.po
odoo/addons/project_recalculate/i18n/gl_ES.po
odoo/addons/project_recalculate/i18n/he.po
odoo/addons/project_recalculate/i18n/hi.po
odoo/addons/project_recalculate/i18n/hr.po
odoo/addons/project_recalculate/i18n/hr_HR.po
odoo/addons/project_recalculate/i18n/hu.po
odoo/addons/project_recalculate/i18n/id.po
odoo14_addon_project_recalculate-14.0.1.0.1.dev13.dist-info/METADATA
odoo14_addon_project_recalculate-14.0.1.0.1.dev13.dist-info/WHEEL
odoo14_addon_project_recalculate-14.0.1.0.1.dev13.dist-info/top_level.txt
odoo14_addon_project_recalculate-14.0.1.0.1.dev13.dist-info/RECORD
